{
    "edges": [
        {
            "component": "edge", 
            "id": 66, 
            "source": "Regional\\nContact management", 
            "target": "Event coordination", 
            "type": "dependency", 
            "value": "dependency"
        }, 
        {
            "component": "edge", 
            "id": 67, 
            "source": "Get Corporate Partner Information from DL", 
            "target": "Regional\\nContact management", 
            "type": "dependency", 
            "value": "dependency"
        }, 
        {
            "component": "edge", 
            "id": 68, 
            "source": "Single charitable registration number", 
            "target": "Regional\\nContact management", 
            "type": "dependency", 
            "value": "dependency"
        }, 
        {
            "component": "edge", 
            "id": 69, 
            "source": "Provide free services", 
            "target": " Free services", 
            "type": "dependency", 
            "value": "dependency"
        }, 
        {
            "component": "edge", 
            "id": 70, 
            "source": "Regional\\nContact management", 
            "target": "Regional Staff feel included", 
            "type": "dependency", 
            "value": "dependency"
        }, 
        {
            "component": "edge", 
            "id": 71, 
            "source": "Up to date corporate partner information", 
            "target": "Regional\\nContact management", 
            "type": "dependency", 
            "value": "dependency"
        }, 
        {
            "component": "edge", 
            "id": 72, 
            "source": "Regional\\nContact management", 
            "target": "Communicate with head office ", 
            "type": "dependency", 
            "value": "dependency"
        }
    ], 
    "name": "CSFDandMarketingSD", 
    "nodes": [
        {
            "component": "node", 
            "container": null, 
            "cost": 0, 
            "from_edges": [], 
            "id": "! Market CS Service", 
            "is_random": false, 
            "name": "! Market CS Service", 
            "to_edges": [], 
            "type": "task", 
            "weighted_cost": 0
        }, 
        {
            "component": "node", 
            "container": null, 
            "cost": 0, 
            "from_edges": [], 
            "id": "Exclusive Relationships [Official Partners] ", 
            "is_random": false, 
            "name": "Exclusive Relationships [Official Partners] ", 
            "to_edges": [], 
            "type": "softgoal", 
            "weighted_cost": 0
        }, 
        {
            "component": "node", 
            "container": null, 
            "cost": 0, 
            "from_edges": [], 
            "id": "Up to date corporate partner information", 
            "is_random": false, 
            "name": "Up to date corporate partner information", 
            "to_edges": [
                71
            ], 
            "type": "softgoal", 
            "weighted_cost": 0
        }, 
        {
            "component": "node", 
            "container": null, 
            "cost": 0, 
            "from_edges": [], 
            "id": "Provide Online Donor Technology", 
            "is_random": false, 
            "name": "Provide Online Donor Technology", 
            "to_edges": [], 
            "type": "task", 
            "weighted_cost": 0
        }, 
        {
            "component": "node", 
            "container": null, 
            "cost": 0, 
            "from_edges": [], 
            "id": "Pledge\\nDuring event", 
            "is_random": false, 
            "name": "Pledge\\nDuring event", 
            "to_edges": [], 
            "type": "task", 
            "weighted_cost": 0
        }, 
        {
            "component": "node", 
            "container": null, 
            "cost": 0, 
            "from_edges": [], 
            "id": "Accountability of services", 
            "is_random": false, 
            "name": "Accountability of services", 
            "to_edges": [], 
            "type": "softgoal", 
            "weighted_cost": 0
        }, 
        {
            "component": "node", 
            "container": null, 
            "cost": 0, 
            "from_edges": [], 
            "id": "Recognize\\nSponsor contribution ", 
            "is_random": false, 
            "name": "Recognize\\nSponsor contribution ", 
            "to_edges": [], 
            "type": "softgoal", 
            "weighted_cost": 0
        }, 
        {
            "component": "node", 
            "container": null, 
            "cost": 0, 
            "from_edges": [], 
            "id": "! Write Articles for Magazines ", 
            "is_random": false, 
            "name": "! Write Articles for Magazines ", 
            "to_edges": [], 
            "type": "task", 
            "weighted_cost": 0
        }, 
        {
            "component": "node", 
            "container": null, 
            "cost": 0, 
            "from_edges": [], 
            "id": "Exclusive Brand and Logo use", 
            "is_random": false, 
            "name": "Exclusive Brand and Logo use", 
            "to_edges": [], 
            "type": "softgoal", 
            "weighted_cost": 0
        }, 
        {
            "component": "node", 
            "container": null, 
            "cost": 0, 
            "from_edges": [], 
            "id": "High Response [Individual Donors] ", 
            "is_random": false, 
            "name": "High Response [Individual Donors] ", 
            "to_edges": [], 
            "type": "softgoal", 
            "weighted_cost": 0
        }, 
        {
            "component": "node", 
            "container": null, 
            "cost": 0, 
            "from_edges": [], 
            "id": "Single charitable registration number", 
            "is_random": false, 
            "name": "Single charitable registration number", 
            "to_edges": [
                68
            ], 
            "type": "resource", 
            "weighted_cost": 0
        }, 
        {
            "component": "node", 
            "container": null, 
            "cost": 0, 
            "from_edges": [], 
            "id": "National Event Calendar", 
            "is_random": false, 
            "name": "National Event Calendar", 
            "to_edges": [], 
            "type": "resource", 
            "weighted_cost": 0
        }, 
        {
            "component": "node", 
            "container": null, 
            "cost": 0, 
            "from_edges": [], 
            "id": "Quality [Services] ", 
            "is_random": false, 
            "name": "Quality [Services] ", 
            "to_edges": [], 
            "type": "softgoal", 
            "weighted_cost": 0
        }, 
        {
            "component": "node", 
            "container": null, 
            "cost": 0, 
            "from_edges": [], 
            "id": "*Engage employees in events", 
            "is_random": false, 
            "name": "*Engage employees in events", 
            "to_edges": [], 
            "type": "softgoal", 
            "weighted_cost": 0
        }, 
        {
            "component": "node", 
            "container": null, 
            "cost": 0, 
            "from_edges": [], 
            "id": "CS Stories", 
            "is_random": false, 
            "name": "CS Stories", 
            "to_edges": [], 
            "type": "softgoal", 
            "weighted_cost": 0
        }, 
        {
            "component": "node", 
            "container": null, 
            "cost": 0, 
            "from_edges": [], 
            "id": "Provide receipts", 
            "is_random": false, 
            "name": "Provide receipts", 
            "to_edges": [], 
            "type": "task", 
            "weighted_cost": 0
        }, 
        {
            "component": "node", 
            "container": null, 
            "cost": 0, 
            "from_edges": [], 
            "id": "Collect Pledge online", 
            "is_random": false, 
            "name": "Collect Pledge online", 
            "to_edges": [], 
            "type": "task", 
            "weighted_cost": 0
        }, 
        {
            "component": "node", 
            "container": null, 
            "cost": 0, 
            "from_edges": [], 
            "id": "Free advertisement", 
            "is_random": false, 
            "name": "Free advertisement", 
            "to_edges": [], 
            "type": "resource", 
            "weighted_cost": 0
        }, 
        {
            "component": "node", 
            "container": null, 
            "cost": 0, 
            "from_edges": [], 
            "id": "Published CS Stories", 
            "is_random": false, 
            "name": "Published CS Stories", 
            "to_edges": [], 
            "type": "softgoal", 
            "weighted_cost": 0
        }, 
        {
            "component": "node", 
            "container": null, 
            "cost": 0, 
            "from_edges": [], 
            "id": "Increase Access Speed [  Regional Offices to Document Library]", 
            "is_random": false, 
            "name": "Increase Access Speed [  Regional Offices to Document Library]", 
            "to_edges": [], 
            "type": "softgoal", 
            "weighted_cost": 0
        }, 
        {
            "component": "node", 
            "container": null, 
            "cost": 0, 
            "from_edges": [], 
            "id": "Engage Employees in events", 
            "is_random": false, 
            "name": "Engage Employees in events", 
            "to_edges": [], 
            "type": "softgoal", 
            "weighted_cost": 0
        }, 
        {
            "component": "node", 
            "container": null, 
            "cost": 0, 
            "from_edges": [], 
            "id": "Funds", 
            "is_random": false, 
            "name": "Funds", 
            "to_edges": [], 
            "type": "resource", 
            "weighted_cost": 0
        }, 
        {
            "component": "node", 
            "container": null, 
            "cost": 0, 
            "from_edges": [
                70
            ], 
            "id": "Regional Staff feel included", 
            "is_random": false, 
            "name": "Regional Staff feel included", 
            "to_edges": [], 
            "type": "softgoal", 
            "weighted_cost": 0
        }, 
        {
            "component": "node", 
            "container": null, 
            "cost": 0, 
            "from_edges": [], 
            "id": "Sponsorship proposal", 
            "is_random": false, 
            "name": "Sponsorship proposal", 
            "to_edges": [], 
            "type": "task", 
            "weighted_cost": 0
        }, 
        {
            "component": "node", 
            "container": null, 
            "cost": 0, 
            "from_edges": [
                66
            ], 
            "id": "Event coordination", 
            "is_random": false, 
            "name": "Event coordination", 
            "to_edges": [], 
            "type": "task", 
            "weighted_cost": 0
        }, 
        {
            "component": "node", 
            "container": null, 
            "cost": 0, 
            "from_edges": [], 
            "id": "Follow Highest Ethical Guidelines ", 
            "is_random": false, 
            "name": "Follow Highest Ethical Guidelines ", 
            "to_edges": [], 
            "type": "softgoal", 
            "weighted_cost": 0
        }, 
        {
            "component": "node", 
            "container": null, 
            "cost": 0, 
            "from_edges": [], 
            "id": "!Acquire public speaking skills", 
            "is_random": false, 
            "name": "!Acquire public speaking skills", 
            "to_edges": [], 
            "type": "softgoal", 
            "weighted_cost": 0
        }, 
        {
            "component": "node", 
            "container": null, 
            "cost": 0, 
            "from_edges": [], 
            "id": "Create General Ledgers ", 
            "is_random": false, 
            "name": "Create General Ledgers ", 
            "to_edges": [], 
            "type": "task", 
            "weighted_cost": 0
        }, 
        {
            "component": "node", 
            "container": null, 
            "cost": 0, 
            "from_edges": [], 
            "id": "Regional\\nContact management", 
            "is_random": false, 
            "name": "Regional\\nContact management", 
            "to_edges": [], 
            "type": "softgoal", 
            "weighted_cost": 0
        }, 
        {
            "component": "node", 
            "container": null, 
            "cost": 0, 
            "from_edges": [
                67, 
                68, 
                71
            ], 
            "id": "Regional\\nContact management", 
            "is_random": false, 
            "name": "Regional\\nContact management", 
            "to_edges": [
                66, 
                70, 
                72
            ], 
            "type": "softgoal", 
            "weighted_cost": 0
        }, 
        {
            "component": "node", 
            "container": null, 
            "cost": 0, 
            "from_edges": [], 
            "id": "Sponsor Logo", 
            "is_random": false, 
            "name": "Sponsor Logo", 
            "to_edges": [], 
            "type": "resource", 
            "weighted_cost": 0
        }, 
        {
            "component": "node", 
            "container": null, 
            "cost": 0, 
            "from_edges": [], 
            "id": "! Provide compiled call data ", 
            "is_random": false, 
            "name": "! Provide compiled call data ", 
            "to_edges": [], 
            "type": "task", 
            "weighted_cost": 0
        }, 
        {
            "component": "node", 
            "container": null, 
            "cost": 0, 
            "from_edges": [
                69
            ], 
            "id": " Free services", 
            "is_random": false, 
            "name": " Free services", 
            "to_edges": [], 
            "type": "resource", 
            "weighted_cost": 0
        }, 
        {
            "component": "node", 
            "container": null, 
            "cost": 0, 
            "from_edges": [], 
            "id": "Use sponsor marketing channels", 
            "is_random": false, 
            "name": "Use sponsor marketing channels", 
            "to_edges": [], 
            "type": "task", 
            "weighted_cost": 0
        }, 
        {
            "component": "node", 
            "container": null, 
            "cost": 0, 
            "from_edges": [], 
            "id": "Get Corporate Partner Information from DL", 
            "is_random": false, 
            "name": "Get Corporate Partner Information from DL", 
            "to_edges": [
                67
            ], 
            "type": "task", 
            "weighted_cost": 0
        }, 
        {
            "component": "node", 
            "container": null, 
            "cost": 0, 
            "from_edges": [], 
            "id": "Manage Receivables ", 
            "is_random": false, 
            "name": "Manage Receivables ", 
            "to_edges": [], 
            "type": "task", 
            "weighted_cost": 0
        }, 
        {
            "component": "node", 
            "container": null, 
            "cost": 0, 
            "from_edges": [], 
            "id": "Demonstrable Services ", 
            "is_random": false, 
            "name": "Demonstrable Services ", 
            "to_edges": [], 
            "type": "softgoal", 
            "weighted_cost": 0
        }, 
        {
            "component": "node", 
            "container": null, 
            "cost": 0, 
            "from_edges": [], 
            "id": "Provide fundraising services", 
            "is_random": false, 
            "name": "Provide fundraising services", 
            "to_edges": [], 
            "type": "task", 
            "weighted_cost": 0
        }, 
        {
            "component": "node", 
            "container": null, 
            "cost": 0, 
            "from_edges": [], 
            "id": "Provide fundraising services", 
            "is_random": false, 
            "name": "Provide fundraising services", 
            "to_edges": [], 
            "type": "task", 
            "weighted_cost": 0
        }, 
        {
            "component": "node", 
            "container": null, 
            "cost": 0, 
            "from_edges": [], 
            "id": "Provide Document Library System", 
            "is_random": false, 
            "name": "Provide Document Library System", 
            "to_edges": [], 
            "type": "task", 
            "weighted_cost": 0
        }, 
        {
            "component": "node", 
            "container": null, 
            "cost": 0, 
            "from_edges": [], 
            "id": "! Provide money for services", 
            "is_random": false, 
            "name": "! Provide money for services", 
            "to_edges": [], 
            "type": "task", 
            "weighted_cost": 0
        }, 
        {
            "component": "node", 
            "container": null, 
            "cost": 0, 
            "from_edges": [], 
            "id": "Manage Accounts ", 
            "is_random": false, 
            "name": "Manage Accounts ", 
            "to_edges": [], 
            "type": "task", 
            "weighted_cost": 0
        }, 
        {
            "component": "node", 
            "container": null, 
            "cost": 0, 
            "from_edges": [], 
            "id": "! Counselor Speak on Kids Issues in General ", 
            "is_random": false, 
            "name": "! Counselor Speak on Kids Issues in General ", 
            "to_edges": [], 
            "type": "task", 
            "weighted_cost": 0
        }, 
        {
            "component": "node", 
            "container": null, 
            "cost": 0, 
            "from_edges": [], 
            "id": "[Increase] Awareness", 
            "is_random": false, 
            "name": "[Increase] Awareness", 
            "to_edges": [], 
            "type": "softgoal", 
            "weighted_cost": 0
        }, 
        {
            "component": "node", 
            "container": null, 
            "cost": 0, 
            "from_edges": [], 
            "id": "Provide funds", 
            "is_random": false, 
            "name": "Provide funds", 
            "to_edges": [], 
            "type": "task", 
            "weighted_cost": 0
        }, 
        {
            "component": "node", 
            "container": null, 
            "cost": 0, 
            "from_edges": [], 
            "id": "Promotion Resources", 
            "is_random": false, 
            "name": "Promotion Resources", 
            "to_edges": [], 
            "type": "softgoal", 
            "weighted_cost": 0
        }, 
        {
            "component": "node", 
            "container": null, 
            "cost": 0, 
            "from_edges": [], 
            "id": "Provide free services", 
            "is_random": false, 
            "name": "Provide free services", 
            "to_edges": [
                69
            ], 
            "type": "task", 
            "weighted_cost": 0
        }, 
        {
            "component": "node", 
            "container": null, 
            "cost": 0, 
            "from_edges": [], 
            "id": "Experienced [marketing partners]", 
            "is_random": false, 
            "name": "Experienced [marketing partners]", 
            "to_edges": [], 
            "type": "softgoal", 
            "weighted_cost": 0
        }, 
        {
            "component": "node", 
            "container": null, 
            "cost": 0, 
            "from_edges": [], 
            "id": "Credibility [CS Brand] ", 
            "is_random": false, 
            "name": "Credibility [CS Brand] ", 
            "to_edges": [], 
            "type": "softgoal", 
            "weighted_cost": 0
        }, 
        {
            "component": "node", 
            "container": null, 
            "cost": 0, 
            "from_edges": [], 
            "id": "Get sponsors for events", 
            "is_random": false, 
            "name": "Get sponsors for events", 
            "to_edges": [], 
            "type": "task", 
            "weighted_cost": 0
        }, 
        {
            "component": "node", 
            "container": null, 
            "cost": 0, 
            "from_edges": [], 
            "id": "! Services be provided for Kids Bullying Line", 
            "is_random": false, 
            "name": "! Services be provided for Kids Bullying Line", 
            "to_edges": [], 
            "type": "goal", 
            "weighted_cost": 0
        }, 
        {
            "component": "node", 
            "container": null, 
            "cost": 0, 
            "from_edges": [], 
            "id": "Pledge online", 
            "is_random": false, 
            "name": "Pledge online", 
            "to_edges": [], 
            "type": "task", 
            "weighted_cost": 0
        }, 
        {
            "component": "node", 
            "container": null, 
            "cost": 0, 
            "from_edges": [], 
            "id": "Retain [Sponsors] ", 
            "is_random": false, 
            "name": "Retain [Sponsors] ", 
            "to_edges": [], 
            "type": "softgoal", 
            "weighted_cost": 0
        }, 
        {
            "component": "node", 
            "container": null, 
            "cost": 0, 
            "from_edges": [], 
            "id": "Presentation Skills ", 
            "is_random": false, 
            "name": "Presentation Skills ", 
            "to_edges": [], 
            "type": "softgoal", 
            "weighted_cost": 0
        }, 
        {
            "component": "node", 
            "container": null, 
            "cost": 0, 
            "from_edges": [], 
            "id": "Philanthropic donations ", 
            "is_random": false, 
            "name": "Philanthropic donations ", 
            "to_edges": [], 
            "type": "task", 
            "weighted_cost": 0
        }, 
        {
            "component": "node", 
            "container": null, 
            "cost": 0, 
            "from_edges": [], 
            "id": "Manage\\nPartner Relationship", 
            "is_random": false, 
            "name": "Manage\\nPartner Relationship", 
            "to_edges": [], 
            "type": "task", 
            "weighted_cost": 0
        }, 
        {
            "component": "node", 
            "container": null, 
            "cost": 0, 
            "from_edges": [], 
            "id": "! Write Articles for Website ", 
            "is_random": false, 
            "name": "! Write Articles for Website ", 
            "to_edges": [], 
            "type": "task", 
            "weighted_cost": 0
        }, 
        {
            "component": "node", 
            "container": null, 
            "cost": 0, 
            "from_edges": [], 
            "id": "Timely services", 
            "is_random": false, 
            "name": "Timely services", 
            "to_edges": [], 
            "type": "softgoal", 
            "weighted_cost": 0
        }, 
        {
            "component": "node", 
            "container": null, 
            "cost": 0, 
            "from_edges": [], 
            "id": "Up to Date [Information on programs] ", 
            "is_random": false, 
            "name": "Up to Date [Information on programs] ", 
            "to_edges": [], 
            "type": "softgoal", 
            "weighted_cost": 0
        }, 
        {
            "component": "node", 
            "container": null, 
            "cost": 0, 
            "from_edges": [], 
            "id": "Sponsor partner\\ncontacts", 
            "is_random": false, 
            "name": "Sponsor partner\\ncontacts", 
            "to_edges": [], 
            "type": "softgoal", 
            "weighted_cost": 0
        }, 
        {
            "component": "node", 
            "container": null, 
            "cost": 0, 
            "from_edges": [
                72
            ], 
            "id": "Communicate with head office ", 
            "is_random": false, 
            "name": "Communicate with head office ", 
            "to_edges": [], 
            "type": "task", 
            "weighted_cost": 0
        }, 
        {
            "component": "node", 
            "container": null, 
            "cost": 0, 
            "from_edges": [], 
            "id": "Agreement", 
            "is_random": false, 
            "name": "Agreement", 
            "to_edges": [], 
            "type": "resource", 
            "weighted_cost": 0
        }, 
        {
            "component": "node", 
            "container": null, 
            "cost": 0, 
            "from_edges": [], 
            "id": "Project Management Skills ", 
            "is_random": false, 
            "name": "Project Management Skills ", 
            "to_edges": [], 
            "type": "softgoal", 
            "weighted_cost": 0
        }, 
        {
            "component": "node", 
            "container": null, 
            "cost": 0, 
            "from_edges": [], 
            "id": "Quick [Response to Sponsors] ", 
            "is_random": false, 
            "name": "Quick [Response to Sponsors] ", 
            "to_edges": [], 
            "type": "softgoal", 
            "weighted_cost": 0
        }, 
        {
            "component": "node", 
            "container": null, 
            "cost": 0, 
            "from_edges": [], 
            "id": "Responsible Usage [Sponsor Funds] ", 
            "is_random": false, 
            "name": "Responsible Usage [Sponsor Funds] ", 
            "to_edges": [], 
            "type": "softgoal", 
            "weighted_cost": 0
        }, 
        {
            "component": "node", 
            "container": null, 
            "cost": 0, 
            "from_edges": [], 
            "id": "Participate in events", 
            "is_random": false, 
            "name": "Participate in events", 
            "to_edges": [], 
            "type": "task", 
            "weighted_cost": 0
        }
    ]
}